{
  "core.typography": {
    "bpost-brand": {
      "value": "Ubuntu",
      "type": "fontFamilies"
    },
    "regular": {
      "value": "Regular",
      "type": "fontWeights"
    },
    "semi-bold": {
      "value": "Medium",
      "type": "fontWeights"
    },
    "scale": {
      "value": "1.125",
      "type": "fontSizes"
    },
    "text-s": {
      "value": "{unit}",
      "type": "fontSizes"
    },
    "text-lg": {
      "value": "round( {text-m} * {scale})",
      "type": "fontSizes"
    },
    "text-xl": {
      "value": "round({text-lg} * {scale})",
      "type": "fontSizes"
    },
    "text-2xl": {
      "value": "floor({text-xl} * {scale})",
      "type": "fontSizes"
    },
    "text-3xl": {
      "value": "floor({text-2xl} * {scale})",
      "type": "fontSizes"
    },
    "text-4xl": {
      "value": "floor({text-3xl} * {scale})",
      "type": "fontSizes"
    },
    "text-5xl": {
      "value": "round({text-4xl} * {scale})",
      "type": "fontSizes"
    },
    "text-6xl": {
      "value": "round({text-5xl} * {scale})",
      "type": "fontSizes"
    },
    "text-7xl": {
      "value": "round({text-6xl} * {scale})",
      "type": "fontSizes"
    },
    "text-8xl": {
      "value": "floor({text-7xl} * {scale})",
      "type": "fontSizes"
    },
    "text-9xl": {
      "value": "round({text-8xl} * {scale})",
      "type": "fontSizes"
    },
    "text-10xl": {
      "value": "floor({text-9xl} * {scale})",
      "type": "fontSizes"
    },
    "text-11xl": {
      "value": "floor({text-10xl} * {scale})",
      "type": "fontSizes"
    },
    "text-12xl": {
      "value": "round({text-11xl} * {scale})",
      "type": "fontSizes"
    },
    "line-height-sm": {
      "value": "20",
      "type": "lineHeights"
    },
    "line-height-xs": {
      "value": "18",
      "type": "lineHeights"
    },
    "line-height-md": {
      "value": "24",
      "type": "lineHeights"
    },
    "line-height-lg": {
      "value": "30",
      "type": "lineHeights"
    },
    "line-height-xlg": {
      "value": "38",
      "type": "lineHeights"
    },
    "line-height-xxlg": {
      "value": "52",
      "type": "lineHeights"
    },
    "line-height-xxxlg": {
      "value": "76",
      "type": "lineHeights"
    },
    "desktop-headings": {
      "hero": {
        "value": {
          "fontFamily": "{bpost-brand}",
          "fontWeight": "{semi-bold}",
          "lineHeight": "{line-height-xxxlg}",
          "fontSize": "({text-12xl}+1)"
        },
        "type": "typography"
      },
      "headline-1": {
        "value": {
          "fontFamily": "{bpost-brand}",
          "fontWeight": "{semi-bold}",
          "lineHeight": "{line-height-xxlg}",
          "fontSize": "{text-8xl}"
        },
        "type": "typography"
      },
      "headline-2": {
        "value": {
          "fontFamily": "{bpost-brand}",
          "fontWeight": "{semi-bold}",
          "lineHeight": "{line-height-xlg}",
          "fontSize": "{text-5xl}"
        },
        "type": "typography"
      },
      "headline-3": {
        "value": {
          "fontFamily": "{bpost-brand}",
          "fontWeight": "{semi-bold}",
          "lineHeight": "{line-height-lg}",
          "fontSize": "{text-3xl}"
        },
        "type": "typography"
      },
      "headline-4": {
        "value": {
          "fontFamily": "{bpost-brand}",
          "fontWeight": "{semi-bold}",
          "lineHeight": "{line-height-md}",
          "fontSize": "{text-lg}",
          "paragraphSpacing": "0",
          "letterSpacing": "0"
        },
        "type": "typography"
      }
    },
    "mobile-headings": {
      "hero": {
        "value": "{desktop-headings.headline-1}",
        "type": "typography",
        "description": "Android: display.large\niOS: largeTitle"
      },
      "headline-1": {
        "value": "{desktop-headings.headline-2}",
        "type": "typography",
        "description": "Android: headline.large\niOS: title\n"
      },
      "headline-2": {
        "value": "{desktop-headings.headline-3}",
        "type": "typography",
        "description": "Android: headline medium\niOS: title2"
      },
      "headline-3": {
        "value": "{desktop-headings.headline-4}",
        "type": "typography",
        "description": "Android: headline.small\niOS: title3"
      },
      "headline-4": {
        "value": "{body.body-2-medium}",
        "type": "typography",
        "description": "Android: title.large\niOS: headline"
      }
    },
    "action": {
      "action-1": {
        "value": {
          "fontFamily": "{bpost-brand}",
          "fontWeight": "{semi-bold}",
          "lineHeight": "{line-height-md}",
          "fontSize": "{text-lg}",
          "paragraphSpacing": "0",
          "letterSpacing": "0"
        },
        "type": "typography"
      },
      "action-2": {
        "value": {
          "fontFamily": "{bpost-brand}",
          "fontWeight": "{semi-bold}",
          "fontSize": "{text-s}",
          "lineHeight": "{line-height-sm}",
          "paragraphSpacing": "0"
        },
        "type": "typography"
      }
    },
    "body": {
      "body-1": {
        "value": {
          "fontFamily": "{bpost-brand}",
          "fontWeight": "{regular}",
          "fontSize": "{text-lg}",
          "lineHeight": "{line-height-md}",
          "paragraphSpacing": "0"
        },
        "type": "typography"
      },
      "body-1-medium": {
        "value": {
          "fontFamily": "{bpost-brand}",
          "fontWeight": "{semi-bold}",
          "fontSize": "{text-lg}",
          "lineHeight": "{line-height-md}",
          "paragraphSpacing": "0"
        },
        "type": "typography"
      },
      "link-1": {
        "value": {
          "fontFamily": "{bpost-brand}",
          "fontWeight": "{regular}",
          "fontSize": "{text-lg}",
          "lineHeight": "{line-height-md}",
          "paragraphSpacing": "0",
          "textDecoration": "underline"
        },
        "type": "typography"
      },
      "body-2": {
        "value": {
          "fontFamily": "{bpost-brand}",
          "fontWeight": "{regular}",
          "fontSize": "{text-m}",
          "lineHeight": "{line-height-md}",
          "paragraphSpacing": "0"
        },
        "type": "typography"
      },
      "body-2-medium": {
        "value": {
          "fontFamily": "{bpost-brand}",
          "fontWeight": "{semi-bold}",
          "fontSize": "{text-m}",
          "lineHeight": "{line-height-md}",
          "paragraphSpacing": "0"
        },
        "type": "typography"
      },
      "link-2": {
        "value": {
          "fontFamily": "{bpost-brand}",
          "fontWeight": "{regular}",
          "fontSize": "{text-m}",
          "lineHeight": "{line-height-md}",
          "paragraphSpacing": "0",
          "textDecoration": "Underline"
        },
        "type": "typography"
      },
      "body-3": {
        "value": {
          "fontFamily": "{bpost-brand}",
          "fontSize": "{text-s}",
          "lineHeight": "{line-height-sm}",
          "paragraphSpacing": "0",
          "fontWeight": "{regular}"
        },
        "type": "typography"
      },
      "body-3-medium": {
        "value": {
          "fontFamily": "{bpost-brand}",
          "fontWeight": "{semi-bold}",
          "fontSize": "{text-s}",
          "lineHeight": "{line-height-sm}",
          "paragraphSpacing": "0"
        },
        "type": "typography"
      },
      "link-3": {
        "value": {
          "fontFamily": "{bpost-brand}",
          "fontSize": "{text-s}",
          "lineHeight": "{line-height-sm}",
          "paragraphSpacing": "0",
          "fontWeight": "{regular}",
          "textDecoration": "underline"
        },
        "type": "typography"
      },
      "body-4": {
        "value": {
          "fontFamily": "{bpost-brand}",
          "fontSize": "{text-xs}",
          "lineHeight": "{line-height-xs}",
          "paragraphSpacing": "0",
          "fontWeight": "{regular}"
        },
        "type": "typography"
      },
      "body-4-medium": {
        "value": {
          "fontFamily": "{bpost-brand}",
          "fontSize": "{text-xs}",
          "lineHeight": "{line-height-xs}",
          "paragraphSpacing": "0",
          "fontWeight": "{semi-bold}"
        },
        "type": "typography"
      },
      "link-4": {
        "value": {
          "fontFamily": "{bpost-brand}",
          "fontSize": "{text-xs}",
          "lineHeight": "{line-height-xs}",
          "paragraphSpacing": "0",
          "fontWeight": "{regular}",
          "textDecoration": "underline"
        },
        "type": "typography"
      }
    },
    "unit": {
      "value": "14",
      "type": "fontSizes"
    },
    "text-m": {
      "value": "round( {unit} * {scale})",
      "type": "fontSizes"
    },
    "text-xs": {
      "value": "round( {text-s} / {scale})",
      "type": "fontSizes"
    }
  },
  "core.color": {
    "seed": {
      "black": {
        "value": "#000000",
        "type": "color"
      },
      "white": {
        "value": "#ffffff",
        "type": "color"
      },
      "red": {
        "value": "#DD1829",
        "type": "color"
      },
      "blue": {
        "value": "#347794",
        "type": "color"
      },
      "green": {
        "value": "#448344",
        "type": "color"
      },
      "orange": {
        "value": "#CB4D01",
        "type": "color"
      },
      "yellow": {
        "value": "#FFC222",
        "type": "color"
      },
      "purple": {
        "value": "#5355BB",
        "type": "color"
      }
    },
    "palettes": {
      "primary": {
        "red": {
          "10": {
            "value": "#580A10",
            "type": "color"
          },
          "20": {
            "value": "#850E19",
            "type": "color"
          },
          "25": {
            "value": "#990411",
            "type": "color"
          },
          "30": {
            "value": "#B11321",
            "type": "color"
          },
          "40": {
            "value": "{seed.red}",
            "type": "color"
          },
          "50": {
            "value": "#E44654",
            "type": "color"
          },
          "60": {
            "value": "#EB747F",
            "type": "color"
          },
          "70": {
            "value": "#F1A3A9",
            "type": "color"
          },
          "80": {
            "value": "#F8D1D4",
            "type": "color"
          },
          "85": {
            "value": "#FED7D3",
            "type": "color"
          },
          "90": {
            "value": "#FFEDEB",
            "type": "color"
          },
          "95": {
            "value": "#FFF8F8",
            "type": "color"
          },
          "99": {
            "value": "#FFFBFF",
            "type": "color"
          }
        }
      },
      "accent": {
        "blue": {
          "10": {
            "value": "#0D1E25",
            "type": "color"
          },
          "20": {
            "value": "#1A3C4A",
            "type": "color"
          },
          "30": {
            "value": "#27596F",
            "type": "color"
          },
          "40": {
            "value": "{seed.blue}",
            "type": "color"
          },
          "50": {
            "value": "#4195B9",
            "type": "color"
          },
          "60": {
            "value": "#67AAC7",
            "type": "color"
          },
          "70": {
            "value": "#8DBFD5",
            "type": "color"
          },
          "80": {
            "value": "#B3D5E3",
            "type": "color"
          },
          "90": {
            "value": "#D9EAF1",
            "type": "color"
          },
          "95": {
            "value": "#EEF9FE",
            "type": "color"
          },
          "99": {
            "value": "#F8FDFF",
            "type": "color"
          }
        },
        "yellow": {
          "10": {
            "value": "#664E0E",
            "type": "color"
          },
          "20": {
            "value": "#997414",
            "type": "color"
          },
          "30": {
            "value": "#CC9B1B",
            "type": "color"
          },
          "40": {
            "value": "{seed.yellow}",
            "type": "color"
          },
          "50": {
            "value": "#FFCE4E",
            "type": "color"
          },
          "60": {
            "value": "#FFDA7A",
            "type": "color"
          },
          "70": {
            "value": "#FFE7A7",
            "type": "color"
          },
          "80": {
            "value": "#FFF3D3",
            "type": "color"
          },
          "90": {
            "value": "#FFF7E2",
            "type": "color"
          },
          "95": {
            "value": "#FFFBF2",
            "type": "color"
          },
          "99": {
            "value": "#FFFEFA",
            "type": "color"
          }
        },
        "green": {
          "10": {
            "value": "#1B341B",
            "type": "color"
          },
          "20": {
            "value": "#294F29",
            "type": "color"
          },
          "30": {
            "value": "#366936",
            "type": "color"
          },
          "40": {
            "value": "{seed.green}",
            "type": "color"
          },
          "50": {
            "value": "#699C69",
            "type": "color"
          },
          "60": {
            "value": "#8FB58F",
            "type": "color"
          },
          "70": {
            "value": "#B4CDB4",
            "type": "color"
          },
          "80": {
            "value": "#DAE6DA",
            "type": "color"
          },
          "90": {
            "value": "#E7F3E7",
            "type": "color"
          },
          "95": {
            "value": "#F1FAF1",
            "type": "color"
          },
          "99": {
            "value": "#F5FDF5",
            "type": "color"
          }
        },
        "orange": {
          "10": {
            "value": "#511F00",
            "type": "color"
          },
          "20": {
            "value": "#7A2E01",
            "type": "color"
          },
          "30": {
            "value": "#A23E01",
            "type": "color"
          },
          "40": {
            "value": "{seed.orange}",
            "type": "color"
          },
          "50": {
            "value": "#D57134",
            "type": "color"
          },
          "60": {
            "value": "#E09467",
            "type": "color"
          },
          "70": {
            "value": "#EAB899",
            "type": "color"
          },
          "80": {
            "value": "#F5DBCC",
            "type": "color"
          },
          "90": {
            "value": "#FFEDE6",
            "type": "color"
          },
          "95": {
            "value": "#FFF6F2",
            "type": "color"
          },
          "99": {
            "value": "#FFFCFB",
            "type": "color"
          }
        },
        "purple": {
          "10": {
            "value": "#F2F3FF",
            "type": "color"
          },
          "20": {
            "value": "#CECEFF",
            "type": "color"
          },
          "30": {
            "value": "#A9AAFF",
            "type": "color"
          },
          "40": {
            "value": "#7F81F5",
            "type": "color"
          },
          "50": {
            "value": "#686AD8",
            "type": "color"
          },
          "60": {
            "value": "{seed.purple}",
            "type": "color"
          },
          "70": {
            "value": "#40429E",
            "type": "color"
          },
          "80": {
            "value": "#303181",
            "type": "color"
          },
          "90": {
            "value": "#212364",
            "type": "color"
          },
          "100": {
            "value": "#151646",
            "type": "color"
          }
        }
      },
      "neutral": {
        "neutral": {
          "4": {
            "value": "#0B0F0F",
            "type": "color"
          },
          "6": {
            "value": "#101414",
            "type": "color"
          },
          "10": {
            "value": "#191C1D",
            "type": "color"
          },
          "12": {
            "value": "#1D2020",
            "type": "color"
          },
          "14": {
            "value": "#272B2B",
            "type": "color"
          },
          "16": {
            "value": "#323536",
            "type": "color"
          },
          "17": {
            "value": "#363A3A",
            "type": "color"
          },
          "20": {
            "value": "#444748",
            "type": "color"
          },
          "30": {
            "value": "#444747",
            "type": "color"
          },
          "40": {
            "value": "#5C5F5F",
            "type": "color"
          },
          "50": {
            "value": "#747878",
            "type": "color"
          },
          "60": {
            "value": "#8E9192",
            "type": "color"
          },
          "70": {
            "value": "#A9ACAC",
            "type": "color"
          },
          "80": {
            "value": "#C4C7C7",
            "type": "color"
          },
          "87": {
            "value": "#D8DADA",
            "type": "color"
          },
          "90": {
            "value": "#E1E3E3",
            "type": "color"
          },
          "92": {
            "value": "#E6E9E8",
            "type": "color"
          },
          "94": {
            "value": "#ECEEEE",
            "type": "color"
          },
          "95": {
            "value": "#EFF1F1",
            "type": "color"
          },
          "96": {
            "value": "#F2F4F4",
            "type": "color"
          },
          "98": {
            "value": "#F7FAF9",
            "type": "color"
          },
          "99": {
            "value": "#FCFCFC",
            "type": "color"
          }
        },
        "nVariant": {
          "10": {
            "value": "#141D1F",
            "type": "color"
          },
          "20": {
            "value": "#293234",
            "type": "color"
          },
          "30": {
            "value": "#3F484A",
            "type": "color"
          },
          "40": {
            "value": "#576062",
            "type": "color"
          },
          "50": {
            "value": "#71797A",
            "type": "color"
          },
          "60": {
            "value": "#899294",
            "type": "color"
          },
          "70": {
            "value": "#A3ADAF",
            "type": "color"
          },
          "80": {
            "value": "#BFC8CA",
            "type": "color"
          },
          "90": {
            "value": "#DBE4E6",
            "type": "color"
          },
          "95": {
            "value": "#E9F2F5",
            "type": "color"
          },
          "99": {
            "value": "#FCFCFC",
            "type": "color"
          }
        }
      }
    },
    "color": {
      "primaryLowest": {
        "light": {
          "value": "{palettes.primary.red.90}",
          "type": "color"
        },
        "dark": {
          "value": "{palettes.primary.red.90}",
          "type": "color"
        }
      },
      "primaryLower": {
        "light": {
          "value": "{palettes.primary.red.85}",
          "type": "color"
        },
        "dark": {
          "value": "{palettes.primary.red.85}",
          "type": "color"
        }
      },
      "primaryLow": {
        "light": {
          "value": "{palettes.primary.red.70}",
          "type": "color"
        },
        "dark": {
          "value": "{palettes.primary.red.70}",
          "type": "color"
        }
      },
      "primaryDefault": {
        "light": {
          "value": "{palettes.primary.red.40}",
          "type": "color"
        },
        "dark": {
          "value": "{palettes.primary.red.40}",
          "type": "color"
        }
      },
      "primaryHigh": {
        "light": {
          "value": "{palettes.primary.red.30}",
          "type": "color"
        },
        "dark": {
          "value": "{palettes.primary.red.30}",
          "type": "color"
        }
      },
      "primaryHigher": {
        "light": {
          "value": "{palettes.primary.red.25}",
          "type": "color"
        },
        "dark": {
          "value": "{palettes.primary.red.25}",
          "type": "color"
        }
      },
      "secondaryLow": {
        "light": {
          "value": "{palettes.accent.blue.90}",
          "type": "color"
        },
        "dark": {
          "value": "{palettes.accent.blue.10}",
          "type": "color",
          "$extensions": {
            "studio.tokens": {
              "modify": {
                "type": "alpha",
                "value": "0.8",
                "space": "srgb"
              }
            }
          }
        }
      },
      "secondaryDefault": {
        "light": {
          "value": "{palettes.accent.blue.40}",
          "type": "color"
        },
        "dark": {
          "value": "{palettes.accent.blue.40}",
          "type": "color"
        }
      },
      "secondaryHigh": {
        "light": {
          "value": "{palettes.accent.blue.30}",
          "type": "color"
        },
        "dark": {
          "value": "{palettes.accent.blue.70}",
          "type": "color"
        }
      },
      "secondaryHigher": {
        "light": {
          "value": "{palettes.accent.blue.10}",
          "type": "color"
        },
        "dark": {
          "value": "{palettes.accent.blue.90}",
          "type": "color"
        }
      },
      "infoLow": {
        "light": {
          "value": "{palettes.accent.purple.20}",
          "type": "color"
        },
        "dark": {
          "value": "{palettes.accent.purple.80}",
          "type": "color",
          "$extensions": {
            "studio.tokens": {
              "modify": {
                "type": "alpha",
                "value": "0.8",
                "space": "srgb"
              }
            }
          }
        }
      },
      "infoDefault": {
        "light": {
          "value": "{palettes.accent.purple.60}",
          "type": "color"
        },
        "dark": {
          "value": "{palettes.accent.purple.60}",
          "type": "color"
        }
      },
      "infoHigh": {
        "light": {
          "value": "{palettes.accent.purple.70}",
          "type": "color"
        },
        "dark": {
          "value": "{palettes.accent.purple.30}",
          "type": "color"
        }
      },
      "infoHigher": {
        "light": {
          "value": "{palettes.accent.purple.80}",
          "type": "color"
        },
        "dark": {
          "value": "{palettes.accent.purple.20}",
          "type": "color"
        }
      },
      "validationLow": {
        "light": {
          "value": "{palettes.accent.green.80}",
          "type": "color"
        },
        "dark": {
          "value": "{palettes.accent.green.10}",
          "type": "color",
          "$extensions": {
            "studio.tokens": {
              "modify": {
                "type": "alpha",
                "value": "0.8",
                "space": "srgb"
              }
            }
          }
        }
      },
      "validationDefault": {
        "light": {
          "value": "{palettes.accent.green.30}",
          "type": "color"
        },
        "dark": {
          "value": "{palettes.accent.green.30}",
          "type": "color"
        }
      },
      "validationHigh": {
        "light": {
          "value": "{palettes.accent.green.20}",
          "type": "color"
        },
        "dark": {
          "value": "{palettes.accent.green.70}",
          "type": "color"
        }
      },
      "validationHigher": {
        "light": {
          "value": "{palettes.accent.green.10}",
          "type": "color"
        },
        "dark": {
          "value": "{palettes.accent.green.80}",
          "type": "color"
        }
      },
      "warningLow": {
        "light": {
          "value": "{palettes.accent.yellow.90}",
          "type": "color"
        },
        "dark": {
          "value": "{palettes.accent.yellow.10}",
          "type": "color",
          "$extensions": {
            "studio.tokens": {
              "modify": {
                "type": "alpha",
                "value": "0.8",
                "space": "srgb"
              }
            }
          }
        }
      },
      "warningDefault": {
        "light": {
          "value": "{palettes.accent.yellow.40}",
          "type": "color"
        },
        "dark": {
          "value": "{palettes.accent.yellow.40}",
          "type": "color"
        }
      },
      "warningHigh": {
        "light": {
          "value": "{palettes.accent.yellow.30}",
          "type": "color"
        },
        "dark": {
          "value": "{palettes.accent.yellow.80}",
          "type": "color"
        }
      },
      "warningHigher": {
        "light": {
          "value": "{palettes.accent.yellow.10}",
          "type": "color"
        },
        "dark": {
          "value": "{palettes.accent.yellow.90}",
          "type": "color"
        }
      },
      "errorLow": {
        "light": {
          "value": "{palettes.accent.orange.90}",
          "type": "color"
        },
        "dark": {
          "value": "{palettes.accent.orange.10}",
          "type": "color",
          "$extensions": {
            "studio.tokens": {
              "modify": {
                "type": "alpha",
                "value": "0.8",
                "space": "srgb"
              }
            }
          }
        }
      },
      "errorDefault": {
        "light": {
          "value": "{palettes.accent.orange.40}",
          "type": "color"
        },
        "dark": {
          "value": "{palettes.accent.orange.40}",
          "type": "color"
        }
      },
      "errorHigh": {
        "light": {
          "value": "{palettes.accent.orange.30}",
          "type": "color"
        },
        "dark": {
          "value": "{palettes.accent.orange.70}",
          "type": "color"
        }
      },
      "errorHigher": {
        "light": {
          "value": "{palettes.accent.orange.10}",
          "type": "color"
        },
        "dark": {
          "value": "{palettes.accent.orange.90}",
          "type": "color"
        }
      },
      "surfaceLowest": {
        "light": {
          "value": "{palettes.neutral.neutral.98}",
          "type": "color"
        },
        "dark": {
          "value": "{palettes.neutral.neutral.6}",
          "type": "color"
        }
      },
      "surfaceLow": {
        "light": {
          "value": "{seed.white}",
          "type": "color"
        },
        "dark": {
          "value": "{palettes.neutral.neutral.14}",
          "type": "color"
        }
      },
      "surfaceHigh": {
        "light": {
          "value": "{palettes.neutral.neutral.96}",
          "type": "color"
        },
        "dark": {
          "value": "{palettes.neutral.neutral.16}",
          "type": "color"
        }
      },
      "surfaceHighest": {
        "light": {
          "value": "{palettes.neutral.neutral.90}",
          "type": "color"
        },
        "dark": {
          "value": "{palettes.neutral.neutral.20}",
          "type": "color"
        }
      },
      "surfaceInverse": {
        "light": {
          "value": "{palettes.neutral.neutral.20}",
          "type": "color"
        },
        "dark": {
          "value": "{palettes.neutral.neutral.90}",
          "type": "color"
        }
      },
      "textBright": {
        "light": {
          "value": "{seed.white}",
          "type": "color"
        },
        "dark": {
          "value": "{seed.white}",
          "type": "color"
        }
      },
      "textPrimary": {
        "light": {
          "value": "{palettes.neutral.neutral.10}",
          "type": "color"
        },
        "dark": {
          "value": "{palettes.neutral.neutral.90}",
          "type": "color"
        }
      },
      "textSecondary": {
        "light": {
          "value": "{palettes.neutral.nVariant.40}",
          "type": "color"
        },
        "dark": {
          "value": "{palettes.neutral.nVariant.80}",
          "type": "color"
        }
      },
      "textDisabled": {
        "light": {
          "value": "{palettes.neutral.nVariant.80}",
          "type": "color"
        },
        "dark": {
          "value": "{palettes.neutral.nVariant.30}",
          "type": "color"
        }
      },
      "textPrimaryInverse": {
        "light": {
          "value": "{palettes.neutral.neutral.90}",
          "type": "color"
        },
        "dark": {
          "value": "{palettes.neutral.neutral.10}",
          "type": "color"
        }
      },
      "textSecondaryInverse": {
        "light": {
          "value": "{palettes.neutral.neutral.95}",
          "type": "color"
        },
        "dark": {
          "value": "{palettes.neutral.neutral.20}",
          "type": "color"
        }
      },
      "outlineHigh": {
        "light": {
          "value": "{palettes.neutral.nVariant.50}",
          "type": "color"
        },
        "dark": {
          "value": "{palettes.neutral.nVariant.60}",
          "type": "color"
        }
      },
      "outlineDefault": {
        "light": {
          "value": "{palettes.neutral.nVariant.80}",
          "type": "color"
        },
        "dark": {
          "value": "{palettes.neutral.nVariant.30}",
          "type": "color"
        }
      },
      "outlineLow": {
        "light": {
          "value": "{palettes.neutral.neutral.94}",
          "type": "color"
        },
        "dark": {
          "value": "{palettes.neutral.nVariant.20}",
          "type": "color"
        }
      },
      "overlay": {
        "light": {
          "value": "rgba({seed.black},0.6)",
          "type": "color"
        },
        "dark": {
          "value": "rgba({seed.black},0.6)",
          "type": "color"
        }
      },
      "shadow": {
        "light": {
          "value": "{seed.black}",
          "type": "color"
        },
        "dark": {
          "value": "{seed.black}",
          "type": "color"
        }
      },
      "iconsBlue": {
        "light": {
          "value": "{palettes.accent.blue.50}",
          "type": "color"
        },
        "dark": {
          "value": "{palettes.accent.blue.50}",
          "type": "color"
        }
      },
      "iconsGreen": {
        "light": {
          "value": "{palettes.accent.green.50}",
          "type": "color"
        },
        "dark": {
          "value": "{palettes.accent.green.50}",
          "type": "color"
        }
      },
      "iconsRed": {
        "light": {
          "value": "{palettes.primary.red.40}",
          "type": "color"
        },
        "dark": {
          "value": "{palettes.primary.red.40}",
          "type": "color"
        }
      },
      "surfaceHigher": {
        "light": {
          "value": "{palettes.neutral.nVariant.95}",
          "type": "color"
        },
        "dark": {
          "value": "{palettes.neutral.nVariant.20}",
          "type": "color"
        }
      },
      "surfaceInverseVariant": {
        "light": {
          "value": "{palettes.neutral.nVariant.50}",
          "type": "color"
        },
        "dark": {
          "value": "{palettes.neutral.nVariant.60}",
          "type": "color"
        }
      }
    }
  },
  "core.dimensions": {
    "size-baseline": {
      "value": "{baseline}",
      "type": "sizing"
    },
    "size-medium": {
      "value": "{medium}",
      "type": "sizing"
    },
    "size-small": {
      "value": "{small}",
      "type": "sizing"
    },
    "size-x-small": {
      "value": "{x-small}",
      "type": "sizing"
    },
    "size-large": {
      "value": "{large}",
      "type": "sizing"
    },
    "size-x-large": {
      "value": "{x-large}",
      "type": "sizing"
    },
    "size-xx-large": {
      "value": "{xx-large}",
      "type": "sizing"
    },
    "xx-small": {
      "value": "( {baseline} *0.25)",
      "type": "dimension"
    },
    "x-small": {
      "value": "( {baseline} *0.5)",
      "type": "dimension"
    },
    "small": {
      "value": "( {baseline} *0.75)",
      "type": "dimension"
    },
    "baseline": {
      "value": "1rem",
      "type": "dimension"
    },
    "medium": {
      "value": "({baseline}* 1.25)",
      "type": "dimension"
    },
    "large": {
      "value": "({baseline}*1.5)",
      "type": "dimension"
    },
    "x-large": {
      "value": "({baseline}*2)",
      "type": "dimension"
    },
    "xx-large": {
      "value": "({baseline}*2.5)",
      "type": "dimension"
    },
    "xxx-large": {
      "value": "({baseline}*3)",
      "type": "dimension"
    },
    "huge": {
      "value": "({baseline}*3.5)",
      "type": "dimension"
    },
    "x-huge": {
      "value": "({baseline}*4)",
      "type": "dimension"
    },
    "xx-huge": {
      "value": "({baseline}*4.5)",
      "type": "dimension"
    },
    "xxx-huge": {
      "value": "({baseline}*5)",
      "type": "dimension"
    },
    "giga": {
      "value": "({baseline}*6)",
      "type": "dimension"
    },
    "x-giga": {
      "value": "({baseline}*8)",
      "type": "dimension"
    },
    "radius-small": {
      "value": "{x-small}",
      "type": "borderRadius"
    },
    "radius-medium": {
      "value": "{baseline}",
      "type": "borderRadius"
    },
    "radius-large": {
      "value": "{large}",
      "type": "borderRadius"
    },
    "spacing-xx-small": {
      "value": "{xx-small}",
      "type": "spacing"
    },
    "spacing-x-small": {
      "value": "{x-small}",
      "type": "spacing"
    },
    "spacing-small": {
      "value": "{small}",
      "type": "spacing"
    },
    "spacing-baseline": {
      "value": "{baseline}",
      "type": "spacing"
    },
    "spacing-medium": {
      "value": "{medium}",
      "type": "spacing"
    },
    "spacing-large": {
      "value": "{large}",
      "type": "spacing"
    },
    "spacing-x-large": {
      "value": "{x-large}",
      "type": "spacing"
    },
    "spacing-xx-large": {
      "value": "{xx-large}",
      "type": "spacing"
    },
    "spacing-xxx-large": {
      "value": "{xxx-large}",
      "type": "spacing"
    },
    "spacing-huge": {
      "value": "{huge}",
      "type": "spacing"
    },
    "spacing-x-huge": {
      "value": "{x-huge}",
      "type": "spacing"
    },
    "spacing-xx-huge": {
      "value": "{xx-huge}",
      "type": "spacing"
    },
    "spacing-xxx-huge": {
      "value": "{xxx-huge}",
      "type": "spacing"
    },
    "spacing-giga": {
      "value": "{giga}",
      "type": "spacing"
    },
    "spacing-x-giga": {
      "value": "{x-giga}",
      "type": "spacing"
    },
    "radius-none": {
      "value": "{none}",
      "type": "borderRadius"
    },
    "none": {
      "value": "0px",
      "type": "dimension"
    },
    "spacing-none": {
      "value": "{none}",
      "type": "spacing"
    },
    "size-xx-small": {
      "value": "{xx-small}",
      "type": "sizing"
    }
  },
  "design.color.light": {
    "neutral": {
      "surfaces": {
        "lowest": {
          "value": "{color.surfaceLowest.light}",
          "type": "color",
          "description": "Default background colour for all screens"
        },
        "low": {
          "value": "{color.surfaceLow.light}",
          "type": "color",
          "description": "Default color for all containers"
        },
        "high": {
          "value": "{color.surfaceHigh.light}",
          "type": "color",
          "description": "Use to highlight and for hover states of neutral UI elements"
        },
        "higher": {
          "value": "{color.surfaceHigher.light}",
          "type": "color",
          "description": "Selection color for neutral UI elements"
        },
        "highest": {
          "value": "{color.surfaceHighest.light}",
          "type": "color",
          "description": "A darker colour for highlights"
        },
        "inverse": {
          "value": "{color.surfaceInverse.light}",
          "type": "color",
          "description": "inverse color of the default surface"
        },
        "inverseVariant": {
          "value": "{color.surfaceInverseVariant.light}",
          "type": "color",
          "description": "A lighter colour for inverse surfaces"
        },
        "overllay": {
          "value": "{color.overlay.light}",
          "type": "color"
        }
      },
      "outlines": {
        "low": {
          "value": "{color.outlineLow.light}",
          "type": "color",
          "description": "Border colour for neutral UI elements in disabled state and seperators"
        },
        "default": {
          "value": "{color.outlineDefault.light}",
          "type": "color",
          "description": "Default border colour"
        },
        "high": {
          "value": "{color.outlineHigh.light}",
          "type": "color",
          "description": "Border colour for active neutral UI elements"
        }
      },
      "text": {
        "primary": {
          "value": "{color.textPrimary.light}",
          "type": "color",
          "description": "Default text colour"
        },
        "secondary": {
          "value": "{color.textSecondary.light}",
          "type": "color",
          "description": "Secondary text colour. Used for placeholder text and supplemantary information"
        },
        "disabled": {
          "value": "{color.textDisabled.light}",
          "type": "color",
          "description": "Text colour for neutral disabled text in UI elements"
        },
        "primaryInverse": {
          "value": "{color.textPrimaryInverse.light}",
          "type": "color",
          "description": "for inverse surfaces"
        },
        "secondaryInverse": {
          "value": "{color.textSecondaryInverse.light}",
          "type": "color"
        },
        "bright": {
          "value": "{color.textBright.light}",
          "type": "color"
        }
      }
    },
    "primary": {
      "lowest": {
        "value": "{color.primaryLowest.light}",
        "type": "color",
        "description": "Use for Containers of primary importance"
      },
      "lower": {
        "value": "{color.primaryLower.light}",
        "type": "color",
        "description": "Use for pressed states"
      },
      "low": {
        "value": "{color.primaryLow.light}",
        "type": "color",
        "description": "Use for disabled states of primary UI elements"
      },
      "default": {
        "value": "{palettes.primary.red.40}",
        "type": "color",
        "description": "Default colour of primary UI elements and active states of navigation components"
      },
      "high": {
        "value": "{color.primaryHigh.light}",
        "type": "color",
        "description": "Use for hover states of primary elements"
      },
      "higher": {
        "value": "{color.primaryHigher.light}",
        "type": "color",
        "description": "Use on containers  and border color of elements with primary.low background"
      }
    },
    "secondary": {
      "low": {
        "value": "{color.secondaryLow.light}",
        "type": "color",
        "description": "Use for containers of secondary importance"
      },
      "default": {
        "value": "{color.secondaryDefault.light}",
        "type": "color",
        "description": "Use for secondary idle UI elements and borders of secondary containers"
      },
      "high": {
        "value": "{color.secondaryHigh.light}",
        "type": "color",
        "description": "use for hover or active states of secondary elements"
      },
      "higher": {
        "value": "{color.secondaryHigher.light}",
        "type": "color",
        "description": "Use on top of lighter secondary containers"
      }
    },
    "validation": {
      "low": {
        "value": "{color.validationLow.light}",
        "type": "color",
        "description": "use for containers that carry a meaning of validation and disabled state of validation UI elements"
      },
      "default": {
        "value": "{color.validationDefault.light}",
        "type": "color",
        "description": "use for validation UI elements and borders of validation containers"
      },
      "high": {
        "value": "{color.validationHigh.light}",
        "type": "color",
        "description": "use for hover states of validation UI elements"
      },
      "higher": {
        "value": "{color.validationHigher.light}",
        "type": "color",
        "description": "use on top of validation.low containers"
      }
    },
    "warning": {
      "low": {
        "value": "{color.warningLow.light}",
        "type": "color",
        "description": "use for containers that carry a meaning of warning and disabled state of warning UI elements"
      },
      "default": {
        "value": "{color.warningDefault.light}",
        "type": "color",
        "description": "use for warning UI elements and borders of warning containers"
      },
      "high": {
        "value": "{color.warningHigh.light}",
        "type": "color",
        "description": "use for hover states of warning UI elements"
      },
      "higher": {
        "value": "{color.warningHigher.light}",
        "type": "color",
        "description": "use on top of warning containers,  and warning text"
      }
    },
    "error": {
      "low": {
        "value": "{color.errorLow.light}",
        "type": "color",
        "description": "use for containers that carry a meaning of error and disabled state of UI elements in error state"
      },
      "default": {
        "value": "{color.errorDefault.light}",
        "type": "color",
        "description": "use for error UI elements and borders of error containers"
      },
      "high": {
        "value": "{color.errorHigh.light}",
        "type": "color",
        "description": "use for error UI elements and borders of error containers"
      },
      "higher": {
        "value": "{color.errorHigher.light}",
        "type": "color",
        "description": "use on top of error containers and error text"
      }
    },
    "icons": {
      "blue": {
        "value": "{color.iconsBlue.light}",
        "type": "color"
      },
      "green": {
        "value": "{color.iconsGreen.light}",
        "type": "color"
      },
      "red": {
        "value": "{color.iconsRed.light}",
        "type": "color"
      }
    },
    "info": {
      "low": {
        "value": "{color.infoLow.light}",
        "type": "color",
        "description": "use for containers of info messages."
      },
      "default": {
        "value": "{color.infoDefault.light}",
        "type": "color",
        "description": "use for info idle UI elements and borders of info containers."
      },
      "high": {
        "value": "{color.infoHigh.light}",
        "type": "color",
        "description": "use for hover ad active states of info UI elements "
      },
      "higher": {
        "value": "{color.infoHigher.light}",
        "type": "color",
        "description": "Use on top of lighter info containers."
      }
    }
  },
  "design.color.dark": {
    "neutral": {
      "surfaces": {
        "lowest": {
          "value": "{color.surfaceLowest.dark}",
          "type": "color",
          "description": "Default background colour for all screens"
        },
        "low": {
          "value": "{color.surfaceLow.dark}",
          "type": "color",
          "description": "Default color for all containers"
        },
        "high": {
          "value": "{color.surfaceHigh.dark}",
          "type": "color",
          "description": "Use to highlight and for hover states of neutral UI elements"
        },
        "higher": {
          "value": "{color.surfaceHigher.dark}",
          "type": "color",
          "description": "Selection color for neutral UI elements"
        },
        "highest": {
          "value": "{color.surfaceHighest.dark}",
          "type": "color",
          "description": "A darker colour for highdarks"
        },
        "inverse": {
          "value": "{color.surfaceInverse.dark}",
          "type": "color",
          "description": "inverse color of the default surface"
        },
        "inverseVariant": {
          "value": "{color.surfaceInverseVariant.dark}",
          "type": "color",
          "description": "A darker colour for inverse surfaces"
        },
        "overllay": {
          "value": "{color.overlay.dark}",
          "type": "color"
        }
      },
      "outlines": {
        "low": {
          "value": "{color.outlineLow.dark}",
          "type": "color",
          "description": "Border colour for neutral UI elements in disabled state and seperators"
        },
        "default": {
          "value": "{color.outlineDefault.dark}",
          "type": "color",
          "description": "Default border colour"
        },
        "high": {
          "value": "{color.outlineHigh.dark}",
          "type": "color",
          "description": "Border colour for active neutral UI elements"
        }
      },
      "text": {
        "primary": {
          "value": "{color.textPrimary.dark}",
          "type": "color",
          "description": "Default text colour"
        },
        "secondary": {
          "value": "{color.textSecondary.dark}",
          "type": "color",
          "description": "Secondary text colour. Used for placeholder text and supplemantary information"
        },
        "disabled": {
          "value": "{color.textDisabled.dark}",
          "type": "color",
          "description": "Text colour for neutral disabled text in UI elements"
        },
        "primaryInverse": {
          "value": "{color.textPrimaryInverse.dark}",
          "type": "color",
          "description": "for inverse surfaces"
        },
        "secondaryInverse": {
          "value": "{color.textSecondaryInverse.dark}",
          "type": "color"
        },
        "bright": {
          "value": "{color.textBright.dark}",
          "type": "color"
        }
      }
    },
    "primary": {
      "lowest": {
        "value": "{color.primaryLowest.dark}",
        "type": "color",
        "description": "Use for Containers of primary importance"
      },
      "lower": {
        "value": "{color.primaryLower.dark}",
        "type": "color",
        "description": "Use for pressed states"
      },
      "low": {
        "value": "{color.primaryLow.dark}",
        "type": "color",
        "description": "Use for disabled states of primary UI elements"
      },
      "default": {
        "value": "{palettes.primary.red.40}",
        "type": "color",
        "description": "Default colour of primary UI elements and active states of navigation components"
      },
      "high": {
        "value": "{color.primaryHigh.dark}",
        "type": "color",
        "description": "Use for hover states of primary elements"
      },
      "higher": {
        "value": "{color.primaryHigher.dark}",
        "type": "color",
        "description": "Use on containers  and border color of elements with primary.low background"
      }
    },
    "secondary": {
      "low": {
        "value": "{color.secondaryLow.dark}",
        "type": "color",
        "description": "Use for containers of secondary importance"
      },
      "default": {
        "value": "{color.secondaryDefault.dark}",
        "type": "color",
        "description": "Use for secondary idle UI elements and borders of secondary containers"
      },
      "high": {
        "value": "{color.secondaryHigh.dark}",
        "type": "color",
        "description": "use for hover or active states of secondary elements"
      },
      "higher": {
        "value": "{color.secondaryHigher.dark}",
        "type": "color",
        "description": "Use on top of darker secondary containers"
      }
    },
    "validation": {
      "low": {
        "value": "{color.validationLow.dark}",
        "type": "color",
        "description": "use for containers that carry a meaning of validation and disabled state of validation UI elements"
      },
      "default": {
        "value": "{color.validationDefault.dark}",
        "type": "color",
        "description": "use for validation UI elements and borders of validation containers"
      },
      "high": {
        "value": "{color.validationHigh.dark}",
        "type": "color",
        "description": "use for hover states of validation UI elements"
      },
      "higher": {
        "value": "{color.validationHigher.dark}",
        "type": "color",
        "description": "use on top of validation.low containers"
      }
    },
    "warning": {
      "low": {
        "value": "{color.warningLow.dark}",
        "type": "color",
        "description": "use for containers that carry a meaning of warning and disabled state of warning UI elements"
      },
      "default": {
        "value": "{color.warningDefault.dark}",
        "type": "color",
        "description": "use for warning UI elements and borders of warning containers"
      },
      "high": {
        "value": "{color.warningHigh.dark}",
        "type": "color",
        "description": "use for hover states of warning UI elements"
      },
      "higher": {
        "value": "{color.warningHigher.dark}",
        "type": "color",
        "description": "use on top of warning containers,  and warning text"
      }
    },
    "error": {
      "low": {
        "value": "{color.errorLow.dark}",
        "type": "color",
        "description": "use for containers that carry a meaning of error and disabled state of UI elements in error state"
      },
      "default": {
        "value": "{color.errorDefault.dark}",
        "type": "color",
        "description": "use for error UI elements and borders of error containers"
      },
      "high": {
        "value": "{color.errorHigh.dark}",
        "type": "color",
        "description": "use for error UI elements and borders of error containers"
      },
      "higher": {
        "value": "{color.errorHigher.dark}",
        "type": "color",
        "description": "use on top of error containers and error text"
      }
    },
    "icons": {
      "blue": {
        "value": "{color.iconsBlue.dark}",
        "type": "color"
      },
      "green": {
        "value": "{color.iconsGreen.dark}",
        "type": "color"
      },
      "red": {
        "value": "{color.iconsRed.dark}",
        "type": "color"
      }
    },
    "info": {
      "low": {
        "value": "{color.infoLow.dark}",
        "type": "color",
        "description": "use for containers of info messages."
      },
      "default": {
        "value": "{color.infoDefault.dark}",
        "type": "color",
        "description": "use for info idle UI elements and borders of info containers."
      },
      "high": {
        "value": "{color.infoHigh.dark}",
        "type": "color",
        "description": "use for hover ad active states of info UI elements "
      },
      "higher": {
        "value": "{color.infoHigher.dark}",
        "type": "color",
        "description": "Use on top of darker info containers."
      }
    }
  },
  "core.deco": {
    "elevationSmall": {
      "value": {
        "x": "0",
        "y": "1",
        "blur": "6",
        "spread": "0",
        "color": "rgba( {color.shadow.light} , 0.12)",
        "type": "dropShadow"
      },
      "type": "boxShadow"
    },
    "elevationLarge": {
      "value": {
        "x": "0",
        "y": "4",
        "blur": "12",
        "spread": "0",
        "color": "rgba( {color.shadow.light} ,0.1)",
        "type": "dropShadow"
      },
      "type": "boxShadow"
    },
    "elevationInverted": {
      "value": {
        "x": "0",
        "y": "-4",
        "blur": "12",
        "spread": "0",
        "color": "rgba( {color.shadow.light} ,0.1)",
        "type": "dropShadow"
      },
      "type": "boxShadow"
    },
    "scrim": {
      "value": "0.4",
      "type": "opacity"
    },
    "action-idle": {
      "value": {
        "color": "{color.primaryDefault.light}",
        "width": "1",
        "style": "solid"
      },
      "type": "border"
    },
    "action-active": {
      "value": {
        "color": "{color.primaryHigh.light}",
        "width": "1",
        "style": "solid"
      },
      "type": "border"
    },
    "action-inactive": {
      "value": {
        "color": "{color.primaryLow.light}",
        "width": "1",
        "style": "solid"
      },
      "type": "border"
    },
    "disabled-state": {
      "value": "38%",
      "type": "opacity"
    }
  },
  "$themes": [
    {
      "id": "7c75120bec444133af1b5ad87f59925a7f3fb4f1",
      "name": "light-theme",
      "$figmaStyleReferences": {},
      "selectedTokenSets": {
        "design.color.light": "enabled",
        "core.color": "source"
      },
      "$figmaCollectionId": "VariableCollectionId:836:26553",
      "$figmaModeId": "836:4",
      "$figmaVariableReferences": {
        "neutral.surfaces.lowest": "dcc163d4eeff40647188f35b54ff5f713d01b285",
        "neutral.surfaces.low": "75f467d1937e4bcf3edd4864f26a69fffb05b182",
        "neutral.surfaces.high": "5a42dd97d0c51ee89ef4fd3fba77c6ea406b0974",
        "neutral.surfaces.higher": "0efded33d6934fa370492162c5b5c40e88186d8e",
        "neutral.surfaces.highest": "00a6e8b0df4ec1760961273633448d183018bb49",
        "neutral.surfaces.inverse": "647e78173c084e745166d64fc421eb1c4c517c88",
        "neutral.surfaces.inverseVariant": "1fb028878a2214b09b00287c02a357196893fb75",
        "neutral.surfaces.overllay": "5efc2511ccf215ab0064ef1b12af025529c5fe00",
        "neutral.outlines.low": "d8612f8d314f571bc2a2ebe214e879fcad5ee105",
        "neutral.outlines.default": "f5efda117c6c2fdaf5be01913d7b02da4b75e132",
        "neutral.outlines.high": "3246816c5586368d58c3b4f46619c3c9ffeb927a",
        "neutral.text.primary": "7e8d38f7d8745884803d45edc154b952ba0fd7a8",
        "neutral.text.secondary": "3e54220ec667f2bf5cf98d297f60e1e70b118da8",
        "neutral.text.disabled": "d64a72f7c6d9b1dbec9f51957ce0395de3e5403d",
        "neutral.text.primaryInverse": "25290e65a86da8ffe6044e2b9fe40fe719b39407",
        "neutral.text.secondaryInverse": "ff0d179685dcb02c096a98ed7b6d965d65833322",
        "neutral.text.bright": "bc2e119408a448e4681f81f9f7a7085c69d866fa",
        "primary.lowest": "8bd3d126ec578fd82521d4db9db52d1e190e9b22",
        "primary.lower": "f5df80a007ff0878031624d97a41dd86a1c0d0ec",
        "primary.low": "9239579058c2973e902c0b0bb2e47a803d44b519",
        "primary.default": "b87c5d14e9919fc7c5ac437d754e5b22f4b0c25f",
        "primary.high": "a5ea7e415911f311848b3b77d71b7ade83b9023a",
        "primary.higher": "c9d1a9339df625ecae50853f2a735eb6a19d44bf",
        "secondary.low": "306f2ce4280a71c8bb84aabeb92135172e22ac4c",
        "secondary.default": "51e3762f81254facf8704b54b547501df6aef3ba",
        "secondary.high": "78474e48e254039aaae4f20605ac8af777204f5a",
        "secondary.higher": "609fe683ef0c144864f8782b76433bcc93a94818",
        "validation.low": "043b289128e47be06d99462efa82a79b64df1b2a",
        "validation.default": "5abf11155979d93f2021f5dbb33838a952d0a48f",
        "validation.high": "790833589f97f4fa0e9f01e325c9d2a08753b2ca",
        "validation.higher": "9e32c86b137654c4d3f156834bcc95f038ac53fd",
        "warning.low": "2063171665b48174778974d5cb4c250471050dcf",
        "warning.default": "a8c635ff97d2171a3eb658092dd9e23ce8e9efb8",
        "warning.high": "c13cda990149247d3f50999d1fab0a05e9001a27",
        "warning.higher": "1dcbee8929e4e12db8d85c259fc27192f94981fc",
        "error.low": "7843ab5a693f3e029df7a15aba3dcd08a671b437",
        "error.default": "6f00c67aae577850c561f3cb1bd416b3aab0427e",
        "error.high": "fd6104af42142a238888638e47f84367bcdbf1a0",
        "error.higher": "182e2b7578b64f30cde87e99a6b0880b29b2d4b4",
        "icons.blue": "c10368a2b3304ab26f37a33d23309a27f8b31d3d",
        "icons.green": "f97d88073dd62f4619c8faf0a74dab2e79c6944a",
        "icons.red": "f892120db46d86ad4ddb0d5289d7c231bd944200",
        "info.low": "ae9c62cf539729d8599a9e6bd71560b2f5a5ab28",
        "info.default": "4eed45e5c870ddfbbf6222ae1c6b606b9418b85c",
        "info.high": "c1a3e5f5887e8ee5d9ea5c9d244aca0fe9a9332f",
        "info.higher": "1f3f948b9c2b308c8cad703506573d86a00f83a9"
      },
      "group": "bpost-colors"
    },
    {
      "id": "61b7d94f48c37d75014f81f66956192678373fc4",
      "name": "dark-theme",
      "$figmaStyleReferences": {},
      "selectedTokenSets": {
        "core.color": "source",
        "design.color.dark": "enabled"
      },
      "$figmaCollectionId": "VariableCollectionId:836:26553",
      "$figmaModeId": "836:6",
      "$figmaVariableReferences": {
        "neutral.surfaces.lowest": "dcc163d4eeff40647188f35b54ff5f713d01b285",
        "neutral.surfaces.low": "75f467d1937e4bcf3edd4864f26a69fffb05b182",
        "neutral.surfaces.high": "5a42dd97d0c51ee89ef4fd3fba77c6ea406b0974",
        "neutral.surfaces.higher": "0efded33d6934fa370492162c5b5c40e88186d8e",
        "neutral.surfaces.highest": "00a6e8b0df4ec1760961273633448d183018bb49",
        "neutral.surfaces.inverse": "647e78173c084e745166d64fc421eb1c4c517c88",
        "neutral.surfaces.inverseVariant": "1fb028878a2214b09b00287c02a357196893fb75",
        "neutral.surfaces.overllay": "5efc2511ccf215ab0064ef1b12af025529c5fe00",
        "neutral.outlines.low": "d8612f8d314f571bc2a2ebe214e879fcad5ee105",
        "neutral.outlines.default": "f5efda117c6c2fdaf5be01913d7b02da4b75e132",
        "neutral.outlines.high": "3246816c5586368d58c3b4f46619c3c9ffeb927a",
        "neutral.text.primary": "7e8d38f7d8745884803d45edc154b952ba0fd7a8",
        "neutral.text.secondary": "3e54220ec667f2bf5cf98d297f60e1e70b118da8",
        "neutral.text.disabled": "d64a72f7c6d9b1dbec9f51957ce0395de3e5403d",
        "neutral.text.primaryInverse": "25290e65a86da8ffe6044e2b9fe40fe719b39407",
        "neutral.text.secondaryInverse": "ff0d179685dcb02c096a98ed7b6d965d65833322",
        "neutral.text.bright": "bc2e119408a448e4681f81f9f7a7085c69d866fa",
        "primary.lowest": "8bd3d126ec578fd82521d4db9db52d1e190e9b22",
        "primary.lower": "f5df80a007ff0878031624d97a41dd86a1c0d0ec",
        "primary.low": "9239579058c2973e902c0b0bb2e47a803d44b519",
        "primary.default": "b87c5d14e9919fc7c5ac437d754e5b22f4b0c25f",
        "primary.high": "a5ea7e415911f311848b3b77d71b7ade83b9023a",
        "primary.higher": "c9d1a9339df625ecae50853f2a735eb6a19d44bf",
        "secondary.low": "306f2ce4280a71c8bb84aabeb92135172e22ac4c",
        "secondary.default": "51e3762f81254facf8704b54b547501df6aef3ba",
        "secondary.high": "78474e48e254039aaae4f20605ac8af777204f5a",
        "secondary.higher": "609fe683ef0c144864f8782b76433bcc93a94818",
        "validation.low": "043b289128e47be06d99462efa82a79b64df1b2a",
        "validation.default": "5abf11155979d93f2021f5dbb33838a952d0a48f",
        "validation.high": "790833589f97f4fa0e9f01e325c9d2a08753b2ca",
        "validation.higher": "9e32c86b137654c4d3f156834bcc95f038ac53fd",
        "warning.low": "2063171665b48174778974d5cb4c250471050dcf",
        "warning.default": "a8c635ff97d2171a3eb658092dd9e23ce8e9efb8",
        "warning.high": "c13cda990149247d3f50999d1fab0a05e9001a27",
        "warning.higher": "1dcbee8929e4e12db8d85c259fc27192f94981fc",
        "error.low": "7843ab5a693f3e029df7a15aba3dcd08a671b437",
        "error.default": "6f00c67aae577850c561f3cb1bd416b3aab0427e",
        "error.high": "fd6104af42142a238888638e47f84367bcdbf1a0",
        "error.higher": "182e2b7578b64f30cde87e99a6b0880b29b2d4b4",
        "icons.blue": "c10368a2b3304ab26f37a33d23309a27f8b31d3d",
        "icons.green": "f97d88073dd62f4619c8faf0a74dab2e79c6944a",
        "icons.red": "f892120db46d86ad4ddb0d5289d7c231bd944200",
        "info.low": "ae9c62cf539729d8599a9e6bd71560b2f5a5ab28",
        "info.default": "4eed45e5c870ddfbbf6222ae1c6b606b9418b85c",
        "info.high": "c1a3e5f5887e8ee5d9ea5c9d244aca0fe9a9332f",
        "info.higher": "1f3f948b9c2b308c8cad703506573d86a00f83a9"
      },
      "group": "bpost-colors"
    },
    {
      "id": "90d2c97e11a1ed863288408f35ec10a9d8e0fde5",
      "name": "default",
      "$figmaStyleReferences": {},
      "selectedTokenSets": {
        "design.color.light": "source",
        "core.color": "source",
        "design.color.dark": "source",
        "core.dimensions": "source"
      },
      "$figmaCollectionId": "VariableCollectionId:1179:22743",
      "$figmaModeId": "1179:0",
      "$figmaVariableReferences": {},
      "group": "bpost-components"
    },
    {
      "id": "cb593a2ca9249ea35d24cfc608dd1651fb75911e",
      "name": "default",
      "$figmaStyleReferences": {},
      "selectedTokenSets": {
        "core.dimensions": "enabled"
      },
      "$figmaCollectionId": "VariableCollectionId:1180:41172",
      "$figmaModeId": "1180:7",
      "$figmaVariableReferences": {
        "size-baseline": "b28ab09554436305dead3a8dce08e2a143cb153d",
        "size-medium": "be7ce97b80c4e3d613a02aaaf583c4dc08a704dd",
        "size-small": "bd1d5c606464a8d42ee9a9293278d5987c8d48ba",
        "size-x-small": "22f890ad1feb50a490a3034b99dd5995566e56d2",
        "size-large": "2905e528e9f1aa05bf7930eb8f88502502ff6c25",
        "size-x-large": "7660dbc08453ddda0e4792eab4f1f863c512789a",
        "size-xx-large": "483e32de92058ecdff043ab5f9a177aa0bb7a1e8",
        "xx-small": "5e11163b4d6a7fafee36762b015ec856afe02eef",
        "x-small": "04ba36352eda4f9fd4927092ab472fd0e4002e07",
        "small": "f5b47d45857fb3d891df76b5813f43c447d4d01c",
        "baseline": "cbd6d2f70b618a075306a033384f6557ee415f15",
        "medium": "3bca0ff7ce4f9737963c20fbee0d70da8b2d1baa",
        "large": "82264080ecb93e521b0440d08f2b191eed720469",
        "x-large": "643d6f59dcdabdbd6783d3f89ddd31a3caa95f23",
        "xx-large": "dfebfab53a786ea8722967bbb20f2c71b38bbdde",
        "xxx-large": "6701cb5eb6ea79fd5657c352945ae615ee0cf8ff",
        "huge": "f8e40215c8dfb9da49ec4f5523c4256142786b6b",
        "x-huge": "d0e685e273144c1d4164ecc94f6cb77fd40b0c86",
        "xx-huge": "f115c639974016fef800268d916bea35c0aa1778",
        "xxx-huge": "c74ec8716b4277de9176b700e551db9b49a75116",
        "giga": "45d12589b0618af2fb928319dc96a0e5693971d3",
        "x-giga": "c0e8a886ce17f7a9311fd9e6b688365f34927a93",
        "radius-small": "ee075a42c73671c67f27b41b2788023748d13c5b",
        "radius-medium": "757c3567bec6a9f09d2d26a82fb265d172e06945",
        "radius-large": "26e364611dfd48ef0c184a3e2e978050899d1717",
        "spacing-xx-small": "45f689c00c5f48b068746bdcce39c67966bffe14",
        "spacing-x-small": "50f54b3ee1728450b7cdbe6bbebf61fb1d9d12d6",
        "spacing-small": "ab369951811b6fced7fce697a58446e5bf2b9a14",
        "spacing-baseline": "6934e44a4d59cf7ad9a9bb826489d9d842a1543d",
        "spacing-medium": "bc539b3d285ac729c852256d26485ccdf2fbc248",
        "spacing-large": "ac7c2daaf913f160fdeb98983ca619e6b39cf0bf",
        "spacing-x-large": "a9a75169f47ae4e23ac30b908b907f9ee753376f",
        "spacing-xx-large": "16ca3aacc2df4716e70ede02253d893a37cb87ae",
        "spacing-xxx-large": "e0e365c8b05e4f66158b666ff54c3c78f97122bb",
        "spacing-huge": "e469007c9f23b07e282456c7c203e8f2d1d55694",
        "spacing-x-huge": "0b4d1971f3251538f8890246ad1226aa10337364",
        "spacing-xx-huge": "6cd06d9653d72b1a870d94a9777dfba350cf12b5",
        "spacing-xxx-huge": "8053d085a6ca88bf8f99e42f6dc7eaf2d3fdfe90",
        "spacing-giga": "7d0e8220757fecd0814cc30c92d09b8f6c71e530",
        "spacing-x-giga": "f442c12e8d6ade414a78305c8fe4b0d3788f6233",
        "radius-none": "8755b1d904f03ca57e451f8814a7398cf9a6df8e",
        "none": "edae02a0fd4a3aabd5ec87dc6d5bd95e42b97f59",
        "spacing-none": "8d7da2d899718d7510ac191d6f11701bcb5dd30b"
      },
      "group": "bpost-dimensions-test"
    },
    {
      "id": "ea1f1b9f26099c4945dabc7d0ab5f082e3fe02ac",
      "name": "default",
      "$figmaStyleReferences": {},
      "selectedTokenSets": {
        "core.typography": "enabled"
      },
      "$figmaCollectionId": "VariableCollectionId:1179:41171",
      "$figmaModeId": "1179:6",
      "$figmaVariableReferences": {},
      "group": "bpost-typography"
    },
    {
      "id": "2eb1410c8c7c2fdf4558e3eab330a596441f4c33",
      "name": "default",
      "$figmaStyleReferences": {},
      "selectedTokenSets": {
        "core.deco": "enabled",
        "core.color": "source"
      },
      "$figmaCollectionId": "VariableCollectionId:1115:4574",
      "$figmaModeId": "1179:4",
      "$figmaVariableReferences": {},
      "group": "bpost-decorative"
    }
  ],
  "$metadata": {
    "tokenSetOrder": [
      "core.typography",
      "core.color",
      "core.dimensions",
      "design.color.light",
      "design.color.dark",
      "core.deco"
    ]
  }
}